gatorgrade/__init__.py
gatorgrade/main.py
gatorgrade/generate/__init__.py
gatorgrade/generate/generate.py
gatorgrade/input/__init__.py
gatorgrade/input/checks.py
gatorgrade/input/command_line_generator.py
gatorgrade/input/in_file_path.py
gatorgrade/input/parse_config.py
gatorgrade/input/set_up_shell.py
gatorgrade/output/__init__.py
gatorgrade/output/check_result.py
gatorgrade/output/output.py
gatorgrade-0.8.3.dist-info/METADATA
gatorgrade-0.8.3.dist-info/WHEEL
gatorgrade-0.8.3.dist-info/entry_points.txt
gatorgrade-0.8.3.dist-info/licenses/LICENSE
gatorgrade-0.8.3.dist-info/RECORD
