Metadata-Version: 2.4
Name: gatorgrade
Version: 0.8.3
Summary: GatorGrade executes GatorGrader checks!
Author: Michael Abraham, Jacob Allebach, Liam Black, Katherine Burgess, Pallas-Athena Cain, Yanqiao Chen, Ochirsaikhan Davaajambal, Tuguldurnemekh Gantulga, Anthony Grant-Cook, Dylan Holland, Gregory M. Kapfhammer, Peyton Kelly, Luke Lacaria, Douglas Luman, Lauren Nevill, Rebekah Rudd, Titus Smith, Molly Suppo, Jack Turner, Daniel Ullrich, Garrison Vanzin, Rian Watson
License-File: LICENSE
Requires-Python: <4.0,>=3.10
Requires-Dist: click<9,>=8.3.0
Requires-Dist: gatorgrader<2,>=1.1.2
Requires-Dist: pyyaml<7,>=6.0
Requires-Dist: rich<14,>=13.8.1
Requires-Dist: typer<0.21,>=0.20.0
